constrainingorder/solver.py
constrainingorder/__init__.py
constrainingorder/sets.py
constrainingorder/constraints.py
constrainingorder/variables.py
constrainingorder-0.1.dist-info/DESCRIPTION.rst
constrainingorder-0.1.dist-info/metadata.json
constrainingorder-0.1.dist-info/top_level.txt
constrainingorder-0.1.dist-info/WHEEL
constrainingorder-0.1.dist-info/METADATA
constrainingorder-0.1.dist-info/RECORD
