Metadata-Version: 2.0
Name: constrainingorder
Version: 0.1
Summary: Pure python constraint satisfaction solver
Home-page: https://github.com/jreinhardt/constraining-order
Author: Johannes Reinhardt
Author-email: jreinhardt@ist-dein-freund.de
License: MIT
Keywords: csp,constraint,satisfaction,propagation,sets,intervals
Platform: UNKNOWN
Classifier: Development Status :: 3 - Alpha
Classifier: License :: OSI Approved :: MIT License
Classifier: Operating System :: OS Independent
Classifier: Programming Language :: Python :: 2.7
Classifier: Programming Language :: Python :: 3.4
Classifier: Programming Language :: Python :: Implementation :: PyPy
Requires-Dist: future
